[
  {
    "uuid": "lud-bebes-lecteurs-6",
    "title": "bebes lecteurs 6",
    "category": "autre",
    "catLabel": "Autre",
    "catEmoji": "📌",
    "subcats": [],
    "date": "2026-06-24",
    "endDate": "2026-06-24",
    "dateText": "",
    "schedule": "",
    "place": "Médiathèque",
    "city": "Ludres",
    "free": false,
    "reservation": false,
    "image": null,
    "url": "https://www.ludres.com/liste-evenements/bebes-lecteurs-6/",
    "source": "ludres"
  },
  {
    "uuid": "lud-heure-du-conte-petits-2",
    "title": "Heure du conte petits – ANNULÉE",
    "category": "autre",
    "catLabel": "Autre",
    "catEmoji": "📌",
    "subcats": [
      "Culture"
    ],
    "date": "2026-06-24",
    "endDate": "2026-06-24",
    "dateText": "",
    "schedule": "",
    "place": "Médiathèque",
    "city": "Ludres",
    "free": false,
    "reservation": false,
    "image": "https://www.ludres.com/wp-content/uploads/2026/05/heure-conte-petit-annule.jpg",
    "url": "https://www.ludres.com/liste-evenements/heure-du-conte-petits-2/",
    "source": "ludres"
  },
  {
    "uuid": "lud-fete-de-lecole-de-musique-4",
    "title": "Fête de l École de musique – ANNULÉE",
    "category": "musiques-actuelles",
    "catLabel": "Musiques actuelles",
    "catEmoji": "🎸",
    "subcats": [
      "Culture"
    ],
    "date": "2026-06-24",
    "endDate": "2026-06-24",
    "dateText": "",
    "schedule": "",
    "place": "Centre culturel Charcot",
    "city": "Ludres",
    "free": false,
    "reservation": false,
    "image": "https://www.ludres.com/wp-content/uploads/2026/05/fete-edm-annule.jpg",
    "url": "https://www.ludres.com/liste-evenements/fete-de-lecole-de-musique-4/",
    "source": "ludres"
  },
  {
    "uuid": "lud-la-fete-du-periscolaire-3",
    "title": "La Fête du périscolaire – Annulée",
    "category": "spectacle",
    "catLabel": "Spectacles",
    "catEmoji": "🎭",
    "subcats": [
      "Evènements et spectacles"
    ],
    "date": "2026-06-24",
    "endDate": "2026-06-24",
    "dateText": "",
    "schedule": "",
    "place": "Ecole Loti",
    "city": "Ludres",
    "free": false,
    "reservation": false,
    "image": "https://www.ludres.com/wp-content/uploads/2026/06/fete-perisco-annulee.jpg",
    "url": "https://www.ludres.com/liste-evenements/la-fete-du-periscolaire-3/",
    "source": "ludres"
  },
  {
    "uuid": "lud-lancement-commercial-de-la-residence-les-fontenelles",
    "title": "Lancement commercial de la Résidence Les Fontenelles",
    "category": "autre",
    "catLabel": "Autre",
    "catEmoji": "📌",
    "subcats": [
      "Urbanisme"
    ],
    "date": "2026-06-25",
    "endDate": "2026-06-25",
    "dateText": "",
    "schedule": "",
    "place": "Salle Jean Monnet",
    "city": "Ludres",
    "free": false,
    "reservation": false,
    "image": "https://www.ludres.com/wp-content/uploads/2026/06/fontenelle.jpg",
    "url": "https://www.ludres.com/liste-evenements/lancement-commercial-de-la-residence-les-fontenelles/",
    "source": "ludres"
  },
  {
    "uuid": "lud-point-justice-3",
    "title": "Point justice",
    "category": "citoyennete",
    "catLabel": "Citoyenneté",
    "catEmoji": "🤝",
    "subcats": [
      "Citoyenneté"
    ],
    "date": "2026-06-27",
    "endDate": "2026-06-27",
    "dateText": "",
    "schedule": "",
    "place": "Hôtel de Ville",
    "city": "Ludres",
    "free": false,
    "reservation": false,
    "image": "https://www.ludres.com/wp-content/uploads/2022/01/point-justice.jpg",
    "url": "https://www.ludres.com/liste-evenements/point-justice-3/",
    "source": "ludres"
  },
  {
    "uuid": "lud-gala-de-danse-classique-5",
    "title": "Gala de danse classique",
    "category": "musique-classique",
    "catLabel": "Musique classique",
    "catEmoji": "🎻",
    "subcats": [],
    "date": "2026-06-27",
    "endDate": "2026-06-27",
    "dateText": "",
    "schedule": "",
    "place": "Espace Chaudeau",
    "city": "Ludres",
    "free": false,
    "reservation": false,
    "image": "https://www.ludres.com/wp-content/uploads/2026/06/centre-brassens-danse.jpg",
    "url": "https://www.ludres.com/liste-evenements/gala-de-danse-classique-5/",
    "source": "ludres"
  },
  {
    "uuid": "lud-don-du-sang-2",
    "title": "Don du sang",
    "category": "autre",
    "catLabel": "Autre",
    "catEmoji": "📌",
    "subcats": [
      "Santé"
    ],
    "date": "2026-06-29",
    "endDate": "2026-06-29",
    "dateText": "",
    "schedule": "",
    "place": "Espace Séquoia",
    "city": "Ludres",
    "free": false,
    "reservation": false,
    "image": null,
    "url": "https://www.ludres.com/liste-evenements/don-du-sang-2/",
    "source": "ludres"
  }
]