[
  {
    "uuid": "fb-1574315584088787",
    "title": "Danses à la Pép' 2026 : 4 soirées 100% WCS par 3et4",
    "category": "spectacle",
    "catLabel": "Spectacles",
    "catEmoji": "🎭",
    "subcats": [],
    "date": "2026-07-20",
    "endDate": "2026-07-20",
    "dateText": "20 juil. à 19:00",
    "schedule": "19h",
    "place": "Parc de la Pépinière",
    "city": "",
    "free": false,
    "reservation": false,
    "image": "images/fb/1574315584088787.jpg",
    "url": "https://www.facebook.com/events/1574315584088787/",
    "source": "facebook",
    "rsvp": "",
    "online": false
  },
  {
    "uuid": "fb-1501906224401578",
    "title": "Soirées toutes danses à la Pépinère",
    "category": "spectacle",
    "catLabel": "Spectacles",
    "catEmoji": "🎭",
    "subcats": [],
    "date": "2026-07-21",
    "endDate": "2026-07-21",
    "dateText": "21 juil. à 19:00",
    "schedule": "19h",
    "place": "Parc de la Pépinière",
    "city": "Nancy",
    "free": false,
    "reservation": false,
    "image": "images/fb/1501906224401578.jpg",
    "url": "https://www.facebook.com/events/1501906224401578/",
    "source": "facebook",
    "rsvp": "",
    "online": false
  },
  {
    "uuid": "fb-1537522494711217",
    "title": "AssoMovimiento - 2 Rives 2026 - Sociales SBk + Animations (Salsa&Bachata)",
    "category": "autre",
    "catLabel": "Autre",
    "catEmoji": "📌",
    "subcats": [],
    "date": "2026-07-21",
    "endDate": "2026-07-21",
    "dateText": "21 juil. à 19:00",
    "schedule": "19h",
    "place": "Plan D'eau De La Mechelle Tomblaine",
    "city": "Tomblaine",
    "free": false,
    "reservation": false,
    "image": "images/fb/1537522494711217.jpg",
    "url": "https://www.facebook.com/events/1537522494711217/",
    "source": "facebook",
    "rsvp": "",
    "online": false
  },
  {
    "uuid": "fb-1325493616457060",
    "title": "AssoMovimiento - 2 Rives 2026 - Sociales SBk + Animations (Salsa&Bachata)",
    "category": "musiques-actuelles",
    "catLabel": "Musiques actuelles",
    "catEmoji": "🎸",
    "subcats": [],
    "date": "2026-07-21",
    "endDate": "2026-07-21",
    "dateText": "21 juil. à 19:00",
    "schedule": "19h",
    "place": "Plan D'eau De La Mechelle Tomblaine",
    "city": "Tomblaine",
    "free": false,
    "reservation": false,
    "image": "images/fb/1325493616457060.jpg",
    "url": "https://www.facebook.com/events/1325493616457060/",
    "source": "facebook",
    "rsvp": "",
    "online": false
  },
  {
    "uuid": "fb-1293475149419421",
    "title": "Les légendes de Nevers",
    "category": "autre",
    "catLabel": "Autre",
    "catEmoji": "📌",
    "subcats": [],
    "date": "2026-07-21",
    "endDate": "2026-07-21",
    "dateText": "21 juil. à 18:00",
    "schedule": "18h",
    "place": "Palais ducal de Nevers",
    "city": "",
    "free": false,
    "reservation": false,
    "image": "images/fb/1293475149419421.jpg",
    "url": "https://www.facebook.com/events/1293475149419421/",
    "source": "facebook",
    "rsvp": "",
    "online": false
  },
  {
    "uuid": "fb-847275734931579",
    "title": "Café des Langues Nancy",
    "category": "autre",
    "catLabel": "Autre",
    "catEmoji": "📌",
    "subcats": [],
    "date": "2026-07-22",
    "endDate": "2026-07-22",
    "dateText": "22 juil. à 20:00",
    "schedule": "20h",
    "place": "Pub Mac Carthy",
    "city": "Nancy",
    "free": false,
    "reservation": false,
    "image": "images/fb/847275734931579.jpg",
    "url": "https://www.facebook.com/events/847275734931579/",
    "source": "facebook",
    "rsvp": "",
    "online": false
  },
  {
    "uuid": "fb-1589201959400992",
    "title": "JAM DIY - 23 juillet",
    "category": "musiques-actuelles",
    "catLabel": "Musiques actuelles",
    "catEmoji": "🎸",
    "subcats": [],
    "date": "2026-07-23",
    "endDate": "2026-07-23",
    "dateText": "23 juil. à 17:00",
    "schedule": "17h",
    "place": "Parc Olry",
    "city": "",
    "free": false,
    "reservation": false,
    "image": "images/fb/1589201959400992.jpg",
    "url": "https://www.facebook.com/events/1589201959400992/",
    "source": "facebook",
    "rsvp": "",
    "online": false
  },
  {
    "uuid": "fb-2350228292171675",
    "title": "SEA SEX'N'SON 🇨🇺- MUSIQUE CUBAINE - LA CAGEOT'FOLLE 🎷🎸🇨🇺 - FERMETURE À 23H !",
    "category": "musiques-actuelles",
    "catLabel": "Musiques actuelles",
    "catEmoji": "🎸",
    "subcats": [],
    "date": "2026-07-24",
    "endDate": "2026-07-24",
    "dateText": "24 juil. à 17:00",
    "schedule": "17h",
    "place": "Parc Charles III",
    "city": "Nancy",
    "free": false,
    "reservation": false,
    "image": "images/fb/2350228292171675.jpg",
    "url": "https://www.facebook.com/events/2350228292171675/",
    "source": "facebook",
    "rsvp": "",
    "online": false
  },
  {
    "uuid": "fb-1888309155170303",
    "title": "CERCLES : Visite guidée - Les Impromptus du Tapir",
    "category": "activite",
    "catLabel": "Activités & ateliers",
    "catEmoji": "🎨",
    "subcats": [],
    "date": "2026-07-24",
    "endDate": "2026-07-24",
    "dateText": "24 juil. à 16:30",
    "schedule": "16h30",
    "place": "3",
    "city": "Nancy",
    "free": false,
    "reservation": false,
    "image": "images/fb/1888309155170303.jpg",
    "url": "https://www.facebook.com/events/1888309155170303/",
    "source": "facebook",
    "rsvp": "",
    "online": false
  },
  {
    "uuid": "fb-986756483908043",
    "title": "Balade aux lanternes - Nevers",
    "category": "activite",
    "catLabel": "Activités & ateliers",
    "catEmoji": "🎨",
    "subcats": [],
    "date": "2026-07-24",
    "endDate": "2026-07-24",
    "dateText": "24 juil. à 21:00",
    "schedule": "21h",
    "place": "Palais ducal de Nevers",
    "city": "",
    "free": false,
    "reservation": false,
    "image": "images/fb/986756483908043.jpg",
    "url": "https://www.facebook.com/events/986756483908043/",
    "source": "facebook",
    "rsvp": "",
    "online": false
  },
  {
    "uuid": "fb-1250821310254203",
    "title": "Folk à la Pépinière",
    "category": "autre",
    "catLabel": "Autre",
    "catEmoji": "📌",
    "subcats": [],
    "date": "2026-07-25",
    "endDate": "2026-07-25",
    "dateText": "25 juil. à 19:00",
    "schedule": "19h",
    "place": "Parc de la Pépinière",
    "city": "",
    "free": false,
    "reservation": false,
    "image": "images/fb/1250821310254203.jpg",
    "url": "https://www.facebook.com/events/1250821310254203/",
    "source": "facebook",
    "rsvp": "",
    "online": false
  },
  {
    "uuid": "fb-1622689258808262",
    "title": "Ateliers créatifs estivaux pour les enfants",
    "category": "activite",
    "catLabel": "Activités & ateliers",
    "catEmoji": "🎨",
    "subcats": [],
    "date": "2026-07-25",
    "endDate": "2026-07-25",
    "dateText": "25 juil. à 11:00",
    "schedule": "11h",
    "place": "Jardin botanique Jean- ie Pelt",
    "city": "",
    "free": false,
    "reservation": false,
    "image": "images/fb/1622689258808262.jpg",
    "url": "https://www.facebook.com/events/1622689258808262/",
    "source": "facebook",
    "rsvp": "",
    "online": false
  },
  {
    "uuid": "fb-1037777542101411",
    "title": "Amours d'été – Prairie Mairie + Devore",
    "category": "musiques-actuelles",
    "catLabel": "Musiques actuelles",
    "catEmoji": "🎸",
    "subcats": [],
    "date": "2026-07-26",
    "endDate": "2026-07-26",
    "dateText": "26 juil. à 16:30",
    "schedule": "16h30",
    "place": "Parc Sainte- ie",
    "city": "Nancy",
    "free": false,
    "reservation": false,
    "image": "images/fb/1037777542101411.jpg",
    "url": "https://www.facebook.com/events/1037777542101411/",
    "source": "facebook",
    "rsvp": "",
    "online": false
  },
  {
    "uuid": "fb-845464451510860",
    "title": "Le Nuad Boran : journée de formation au massage thaï",
    "category": "activite",
    "catLabel": "Activités & ateliers",
    "catEmoji": "🎨",
    "subcats": [],
    "date": "2026-07-26",
    "endDate": "2026-07-26",
    "dateText": "26 juil. à 09:00",
    "schedule": "9h",
    "place": "14 rue notre dame",
    "city": "Nancy",
    "free": false,
    "reservation": false,
    "image": "images/fb/845464451510860.jpg",
    "url": "https://www.facebook.com/events/845464451510860/",
    "source": "facebook",
    "rsvp": "",
    "online": false
  },
  {
    "uuid": "fb-1038503868643731",
    "title": "Voyage sonore - Nancy",
    "category": "autre",
    "catLabel": "Autre",
    "catEmoji": "📌",
    "subcats": [],
    "date": "2026-07-30",
    "endDate": "2026-07-30",
    "dateText": "30 juil. à 20:30",
    "schedule": "20h30",
    "place": "NYC yoga",
    "city": "Nancy",
    "free": false,
    "reservation": false,
    "image": "images/fb/1038503868643731.jpg",
    "url": "https://www.facebook.com/events/1038503868643731/",
    "source": "facebook",
    "rsvp": "",
    "online": false
  },
  {
    "uuid": "fb-1468145101731178",
    "title": "Amours d'été – Abyssan + Rosaly",
    "category": "musiques-actuelles",
    "catLabel": "Musiques actuelles",
    "catEmoji": "🎸",
    "subcats": [],
    "date": "2026-08-02",
    "endDate": "2026-08-02",
    "dateText": "2 août à 16:30",
    "schedule": "16h30",
    "place": "Parc Sainte- ie",
    "city": "Nancy",
    "free": false,
    "reservation": false,
    "image": "images/fb/1468145101731178.jpg",
    "url": "https://www.facebook.com/events/1468145101731178/",
    "source": "facebook",
    "rsvp": "",
    "online": false
  },
  {
    "uuid": "fb-1534457655356972",
    "title": "BA-ba du bénévolat à l'Atelier des solidarités",
    "category": "activite",
    "catLabel": "Activités & ateliers",
    "catEmoji": "🎨",
    "subcats": [],
    "date": "2026-08-03",
    "endDate": "2026-08-03",
    "dateText": "3 août à 19:00",
    "schedule": "19h",
    "place": "32 rue Sainte-Anne",
    "city": "Nancy",
    "free": false,
    "reservation": false,
    "image": "images/fb/1534457655356972.jpg",
    "url": "https://www.facebook.com/events/1534457655356972/",
    "source": "facebook",
    "rsvp": "",
    "online": false
  },
  {
    "uuid": "fb-1667646297713963",
    "title": "Odoo Academy Facturation - Nancy",
    "category": "autre",
    "catLabel": "Autre",
    "catEmoji": "📌",
    "subcats": [],
    "date": "2026-08-06",
    "endDate": "2026-08-06",
    "dateText": "6 août à 09:00",
    "schedule": "9h",
    "place": "cure Nancy Centre Gare (11 rue Raymond Poincaré",
    "city": "Nancy",
    "free": false,
    "reservation": false,
    "image": "images/fb/1667646297713963.jpg",
    "url": "https://www.facebook.com/events/1667646297713963/",
    "source": "facebook",
    "rsvp": "",
    "online": false
  },
  {
    "uuid": "fb-3564405017056202",
    "title": "Folk à la Pépinière",
    "category": "autre",
    "catLabel": "Autre",
    "catEmoji": "📌",
    "subcats": [],
    "date": "2026-08-08",
    "endDate": "2026-08-08",
    "dateText": "8 août à 19:00",
    "schedule": "19h",
    "place": "Parc de la Pépinière",
    "city": "",
    "free": false,
    "reservation": false,
    "image": "images/fb/3564405017056202.jpg",
    "url": "https://www.facebook.com/events/3564405017056202/",
    "source": "facebook",
    "rsvp": "",
    "online": false
  },
  {
    "uuid": "fb-1745555886638602",
    "title": "Amours d'été – Derwich + The Nucleons Project",
    "category": "musiques-actuelles",
    "catLabel": "Musiques actuelles",
    "catEmoji": "🎸",
    "subcats": [],
    "date": "2026-08-09",
    "endDate": "2026-08-09",
    "dateText": "9 août à 16:30",
    "schedule": "16h30",
    "place": "Parc Sainte- ie",
    "city": "Nancy",
    "free": false,
    "reservation": false,
    "image": "images/fb/1745555886638602.jpg",
    "url": "https://www.facebook.com/events/1745555886638602/",
    "source": "facebook",
    "rsvp": "",
    "online": false
  },
  {
    "uuid": "fb-1009122542084694",
    "title": "Soirée Bœuf Wagyu - La Maison dans le Parc ⭐",
    "category": "festival",
    "catLabel": "Festivals",
    "catEmoji": "🎪",
    "subcats": [],
    "date": "2026-08-13",
    "endDate": "2026-08-13",
    "dateText": "13 août à 19:00",
    "schedule": "19h",
    "place": "3",
    "city": "Nancy",
    "free": false,
    "reservation": false,
    "image": "images/fb/1009122542084694.jpg",
    "url": "https://www.facebook.com/events/1009122542084694/",
    "source": "facebook",
    "rsvp": "",
    "online": false
  },
  {
    "uuid": "fb-1305537541740059",
    "title": "Amours d'été – Sonic Curves",
    "category": "musiques-actuelles",
    "catLabel": "Musiques actuelles",
    "catEmoji": "🎸",
    "subcats": [],
    "date": "2026-08-14",
    "endDate": "2026-08-14",
    "dateText": "14 août - 15 août",
    "schedule": "",
    "place": "Skatepark NANCY",
    "city": "Nancy",
    "free": false,
    "reservation": false,
    "image": "images/fb/1305537541740059.jpg",
    "url": "https://www.facebook.com/events/1305537541740059/",
    "source": "facebook",
    "rsvp": "",
    "online": false
  },
  {
    "uuid": "fb-1849860542326355",
    "title": "Stage de reliure \"CARNET DE VOYAGE\"",
    "category": "activite",
    "catLabel": "Activités & ateliers",
    "catEmoji": "🎨",
    "subcats": [],
    "date": "2026-08-15",
    "endDate": "2026-08-15",
    "dateText": "15 août à 09:00",
    "schedule": "9h",
    "place": "35 rue de la Commanderie",
    "city": "Nancy",
    "free": false,
    "reservation": false,
    "image": "images/fb/1849860542326355.jpg",
    "url": "https://www.facebook.com/events/1849860542326355/",
    "source": "facebook",
    "rsvp": "",
    "online": false
  },
  {
    "uuid": "fb-1944081152911191",
    "title": "OME Festival 2026",
    "category": "festival",
    "catLabel": "Festivals",
    "catEmoji": "🎪",
    "subcats": [],
    "date": "2026-08-20",
    "endDate": "2026-08-20",
    "dateText": "20 août - 23 août",
    "schedule": "",
    "place": "47 Boulevard d'Austrasie",
    "city": "Nancy",
    "free": false,
    "reservation": false,
    "image": "images/fb/1944081152911191.jpg",
    "url": "https://www.facebook.com/events/1944081152911191/",
    "source": "facebook",
    "rsvp": "",
    "online": false
  },
  {
    "uuid": "fb-1435381031686320",
    "title": "Amours d'été – The Celtic Tramps + Kicks + Danse irlandaise",
    "category": "spectacle",
    "catLabel": "Spectacles",
    "catEmoji": "🎭",
    "subcats": [],
    "date": "2026-08-22",
    "endDate": "2026-08-22",
    "dateText": "22 août à 18:00",
    "schedule": "18h",
    "place": "Plage des Deux Rives",
    "city": "Nancy",
    "free": false,
    "reservation": false,
    "image": "images/fb/1435381031686320.jpg",
    "url": "https://www.facebook.com/events/1435381031686320/",
    "source": "facebook",
    "rsvp": "",
    "online": false
  },
  {
    "uuid": "fb-1691113292129972",
    "title": "RESISTANCE FEST 2 - FREDAG DEN 13:e // LOUD NIGHT // ILLEGAL CORPSE // MARVIN HEEMEYER // BANKÄLE",
    "category": "autre",
    "catLabel": "Autre",
    "catEmoji": "📌",
    "subcats": [],
    "date": "2026-08-22",
    "endDate": "2026-08-22",
    "dateText": "22 août à 19:00",
    "schedule": "19h",
    "place": "La BrÂss'",
    "city": "",
    "free": false,
    "reservation": false,
    "image": "images/fb/1691113292129972.jpg",
    "url": "https://www.facebook.com/events/1691113292129972/",
    "source": "facebook",
    "rsvp": "",
    "online": false
  },
  {
    "uuid": "fb-1654638209043952",
    "title": "Stage de reliure \"CARNET À COUTURE COPTE\"",
    "category": "activite",
    "catLabel": "Activités & ateliers",
    "catEmoji": "🎨",
    "subcats": [],
    "date": "2026-08-22",
    "endDate": "2026-08-22",
    "dateText": "22 août à 09:00",
    "schedule": "9h",
    "place": "35 rue de la Commanderie",
    "city": "Nancy",
    "free": false,
    "reservation": false,
    "image": "images/fb/1654638209043952.jpg",
    "url": "https://www.facebook.com/events/1654638209043952/",
    "source": "facebook",
    "rsvp": "",
    "online": false
  },
  {
    "uuid": "fb-1287870726892702",
    "title": "Formation au massage Lomi Lomi : du 22 au 23 août",
    "category": "activite",
    "catLabel": "Activités & ateliers",
    "catEmoji": "🎨",
    "subcats": [],
    "date": "2026-08-22",
    "endDate": "2026-08-22",
    "dateText": "22 août - 23 août",
    "schedule": "",
    "place": "14 rue notre dame",
    "city": "Nancy",
    "free": false,
    "reservation": false,
    "image": "images/fb/1287870726892702.jpg",
    "url": "https://www.facebook.com/events/1287870726892702/",
    "source": "facebook",
    "rsvp": "",
    "online": false
  },
  {
    "uuid": "fb-1926648578738460",
    "title": "Brunch & Spa Thermal | votre rendez-vous bien-être du dimanche🌞",
    "category": "autre",
    "catLabel": "Autre",
    "catEmoji": "📌",
    "subcats": [],
    "date": "2026-08-23",
    "endDate": "2026-08-23",
    "dateText": "23 août à 11:00",
    "schedule": "11h",
    "place": "2 avenue Hippolyte inger",
    "city": "Nancy",
    "free": false,
    "reservation": false,
    "image": "images/fb/1926648578738460.jpg",
    "url": "https://www.facebook.com/events/1926648578738460/",
    "source": "facebook",
    "rsvp": "",
    "online": false
  },
  {
    "uuid": "fb-970501795603120",
    "title": "Amours d'été – Lisko + Khalil + Danses africaines",
    "category": "spectacle",
    "catLabel": "Spectacles",
    "catEmoji": "🎭",
    "subcats": [],
    "date": "2026-08-27",
    "endDate": "2026-08-27",
    "dateText": "27 août à 18:00",
    "schedule": "18h",
    "place": "Plage des Deux Rives",
    "city": "Nancy",
    "free": false,
    "reservation": false,
    "image": "images/fb/970501795603120.jpg",
    "url": "https://www.facebook.com/events/970501795603120/",
    "source": "facebook",
    "rsvp": "",
    "online": false
  },
  {
    "uuid": "fb-1639379687185016",
    "title": "Tsiga'Nancy 2026",
    "category": "exposition",
    "catLabel": "Expositions",
    "catEmoji": "🖼️",
    "subcats": [],
    "date": "2026-08-27",
    "endDate": "2026-08-27",
    "dateText": "27 août - 29 août",
    "schedule": "",
    "place": "MJC Lillebonne",
    "city": "Nancy",
    "free": false,
    "reservation": false,
    "image": "images/fb/1639379687185016.jpg",
    "url": "https://www.facebook.com/events/1639379687185016/",
    "source": "facebook",
    "rsvp": "",
    "online": false
  },
  {
    "uuid": "fb-2197074877813506",
    "title": "Amours d'été – Louise XIV + Leopard Da Vinci + Karaoké",
    "category": "musiques-actuelles",
    "catLabel": "Musiques actuelles",
    "catEmoji": "🎸",
    "subcats": [],
    "date": "2026-08-29",
    "endDate": "2026-08-29",
    "dateText": "29 août à 18:00",
    "schedule": "18h",
    "place": "Plage des Deux Rives",
    "city": "Nancy",
    "free": false,
    "reservation": false,
    "image": "images/fb/2197074877813506.jpg",
    "url": "https://www.facebook.com/events/2197074877813506/",
    "source": "facebook",
    "rsvp": "",
    "online": false
  },
  {
    "uuid": "fb-1234910572083976",
    "title": "STAGE 1 JOUR - FINISTÈRE - ALGUES ET PLANTES SAUVAGES COMESTIBLES",
    "category": "activite",
    "catLabel": "Activités & ateliers",
    "catEmoji": "🎨",
    "subcats": [],
    "date": "2026-08-30",
    "endDate": "2026-08-30",
    "dateText": "30 août à 09:00",
    "schedule": "9h",
    "place": "Finistère",
    "city": "",
    "free": false,
    "reservation": false,
    "image": "images/fb/1234910572083976.jpg",
    "url": "https://www.facebook.com/events/1234910572083976/",
    "source": "facebook",
    "rsvp": "",
    "online": false
  },
  {
    "uuid": "fb-1027233713170736",
    "title": "Foire à l'équipement",
    "category": "festival",
    "catLabel": "Festivals",
    "catEmoji": "🎪",
    "subcats": [],
    "date": "2026-09-04",
    "endDate": "2026-09-04",
    "dateText": "4 sept. - 5 sept.",
    "schedule": "",
    "place": "Salle des fêtes de Gentilly",
    "city": "",
    "free": false,
    "reservation": false,
    "image": "images/fb/1027233713170736.jpg",
    "url": "https://www.facebook.com/events/1027233713170736/",
    "source": "facebook",
    "rsvp": "",
    "online": false
  },
  {
    "uuid": "fb-1493722549216535",
    "title": "Stage de reliure \"CARNET À COUTURE JAPONAISE\"",
    "category": "activite",
    "catLabel": "Activités & ateliers",
    "catEmoji": "🎨",
    "subcats": [],
    "date": "2026-09-05",
    "endDate": "2026-09-05",
    "dateText": "5 sept. à 09:00",
    "schedule": "9h",
    "place": "35 rue de la Commanderie",
    "city": "Nancy",
    "free": false,
    "reservation": false,
    "image": "images/fb/1493722549216535.jpg",
    "url": "https://www.facebook.com/events/1493722549216535/",
    "source": "facebook",
    "rsvp": "",
    "online": false
  },
  {
    "uuid": "fb-969107719346378",
    "title": "BA-ba du bénévolat à l'Atelier des solidarités",
    "category": "activite",
    "catLabel": "Activités & ateliers",
    "catEmoji": "🎨",
    "subcats": [],
    "date": "2026-09-07",
    "endDate": "2026-09-07",
    "dateText": "7 sept. à 19:00",
    "schedule": "19h",
    "place": "32 rue Sainte-Anne",
    "city": "Nancy",
    "free": false,
    "reservation": false,
    "image": "images/fb/969107719346378.jpg",
    "url": "https://www.facebook.com/events/969107719346378/",
    "source": "facebook",
    "rsvp": "",
    "online": false
  },
  {
    "uuid": "fb-843216955269850",
    "title": "FÊTE DE LA MOBILITÉ",
    "category": "festival",
    "catLabel": "Festivals",
    "catEmoji": "🎪",
    "subcats": [],
    "date": "2026-09-10",
    "endDate": "2026-09-10",
    "dateText": "10 sept. à 08:00",
    "schedule": "8h",
    "place": "Parc d'Agrément-Champ-le-Boeuf",
    "city": "",
    "free": false,
    "reservation": false,
    "image": "images/fb/843216955269850.jpg",
    "url": "https://www.facebook.com/events/843216955269850/",
    "source": "facebook",
    "rsvp": "",
    "online": false
  },
  {
    "uuid": "fb-982488974158014",
    "title": "Showcase à Nancy (54) Festival Le livre sur la place",
    "category": "festival",
    "catLabel": "Festivals",
    "catEmoji": "🎪",
    "subcats": [],
    "date": "2026-09-13",
    "endDate": "2026-09-13",
    "dateText": "13 sept. à 17:00",
    "schedule": "17h",
    "place": "Nancy \" Le Livre Sur La Place\"",
    "city": "Nancy",
    "free": false,
    "reservation": false,
    "image": "images/fb/982488974158014.jpg",
    "url": "https://www.facebook.com/events/982488974158014/",
    "source": "facebook",
    "rsvp": "",
    "online": false
  },
  {
    "uuid": "fb-1536333057944834",
    "title": "Devenez Praticienne Power Legs® et démarrez avec confiance ✨",
    "category": "autre",
    "catLabel": "Autre",
    "catEmoji": "📌",
    "subcats": [],
    "date": "2026-09-14",
    "endDate": "2026-09-14",
    "dateText": "14 sept. à 20:00",
    "schedule": "20h",
    "place": "Nancy",
    "city": "Nancy",
    "free": false,
    "reservation": false,
    "image": "images/fb/1536333057944834.jpg",
    "url": "https://www.facebook.com/events/1536333057944834/",
    "source": "facebook",
    "rsvp": "",
    "online": false
  },
  {
    "uuid": "fb-963087859633416",
    "title": "Festival des Musiques Malfamées n°7",
    "category": "musiques-actuelles",
    "catLabel": "Musiques actuelles",
    "catEmoji": "🎸",
    "subcats": [],
    "date": "2026-09-17",
    "endDate": "2026-09-17",
    "dateText": "17 sept. - 19 sept.",
    "schedule": "",
    "place": "Nancy",
    "city": "Nancy",
    "free": false,
    "reservation": false,
    "image": "images/fb/963087859633416.jpg",
    "url": "https://www.facebook.com/events/963087859633416/",
    "source": "facebook",
    "rsvp": "",
    "online": false
  },
  {
    "uuid": "fb-2076204126606638",
    "title": "Soirée caritative 2026",
    "category": "festival",
    "catLabel": "Festivals",
    "catEmoji": "🎪",
    "subcats": [],
    "date": "2026-09-18",
    "endDate": "2026-09-18",
    "dateText": "18 sept. à 19:00",
    "schedule": "19h",
    "place": "Salon de l'Hotel de ville Nancy",
    "city": "Nancy",
    "free": false,
    "reservation": false,
    "image": "images/fb/2076204126606638.jpg",
    "url": "https://www.facebook.com/events/2076204126606638/",
    "source": "facebook",
    "rsvp": "",
    "online": false
  },
  {
    "uuid": "fb-1631400204678195",
    "title": "Formation Difficultés graphiques chez l’enfant : quel accompagnement en ergothérapie ?",
    "category": "musiques-actuelles",
    "catLabel": "Musiques actuelles",
    "catEmoji": "🎸",
    "subcats": [],
    "date": "2026-09-18",
    "endDate": "2026-09-18",
    "dateText": "18 sept. à 09:00",
    "schedule": "9h",
    "place": "4",
    "city": "Nancy",
    "free": false,
    "reservation": false,
    "image": "images/fb/1631400204678195.jpg",
    "url": "https://www.facebook.com/events/1631400204678195/",
    "source": "facebook",
    "rsvp": "",
    "online": false
  },
  {
    "uuid": "fb-1537121464493570",
    "title": "Fête de la Soupe",
    "category": "festival",
    "catLabel": "Festivals",
    "catEmoji": "🎪",
    "subcats": [],
    "date": "2026-09-19",
    "endDate": "2026-09-19",
    "dateText": "19 sept. à 14:00",
    "schedule": "14h",
    "place": "L'Octroi Nancy",
    "city": "Nancy",
    "free": false,
    "reservation": false,
    "image": "images/fb/1537121464493570.jpg",
    "url": "https://www.facebook.com/events/1537121464493570/",
    "source": "facebook",
    "rsvp": "",
    "online": false
  },
  {
    "uuid": "fb-1319472546912597",
    "title": "150 tours acte 3",
    "category": "autre",
    "catLabel": "Autre",
    "catEmoji": "📌",
    "subcats": [],
    "date": "2026-09-20",
    "endDate": "2026-09-20",
    "dateText": "20 sept. à 10:30",
    "schedule": "10h30",
    "place": "Karting Oberlin",
    "city": "",
    "free": false,
    "reservation": false,
    "image": "images/fb/1319472546912597.jpg",
    "url": "https://www.facebook.com/events/1319472546912597/",
    "source": "facebook",
    "rsvp": "",
    "online": false
  },
  {
    "uuid": "fb-1379089137607236",
    "title": "HISTOIRES DE PLACARD",
    "category": "exposition",
    "catLabel": "Expositions",
    "catEmoji": "🖼️",
    "subcats": [],
    "date": "2026-09-20",
    "endDate": "2026-09-20",
    "dateText": "20 sept. à 11:00",
    "schedule": "11h",
    "place": "10 rue du Baron Louis",
    "city": "Nancy",
    "free": false,
    "reservation": false,
    "image": "images/fb/1379089137607236.jpg",
    "url": "https://www.facebook.com/events/1379089137607236/",
    "source": "facebook",
    "rsvp": "",
    "online": false
  },
  {
    "uuid": "fb-2195449174621928",
    "title": "Sync : Peet + Sozzaa • L'Autre Canal Nancy",
    "category": "musiques-actuelles",
    "catLabel": "Musiques actuelles",
    "catEmoji": "🎸",
    "subcats": [],
    "date": "2026-09-26",
    "endDate": "2026-09-26",
    "dateText": "26 sept. à 20:30",
    "schedule": "20h30",
    "place": "45",
    "city": "Nancy",
    "free": false,
    "reservation": false,
    "image": "images/fb/2195449174621928.jpg",
    "url": "https://www.facebook.com/events/2195449174621928/",
    "source": "facebook",
    "rsvp": "",
    "online": false
  },
  {
    "uuid": "fb-1576821003548733",
    "title": "Solutions ergothérapiques face aux troubles de la déglutition",
    "category": "musiques-actuelles",
    "catLabel": "Musiques actuelles",
    "catEmoji": "🎸",
    "subcats": [],
    "date": "2026-09-28",
    "endDate": "2026-09-28",
    "dateText": "28 sept. - 29 sept.",
    "schedule": "",
    "place": "4 rue des sables à Nancy",
    "city": "Nancy",
    "free": false,
    "reservation": false,
    "image": "images/fb/1576821003548733.jpg",
    "url": "https://www.facebook.com/events/1576821003548733/",
    "source": "facebook",
    "rsvp": "",
    "online": false
  },
  {
    "uuid": "fb-837481552575582",
    "title": "LE VENTRE DE PARIS",
    "category": "autre",
    "catLabel": "Autre",
    "catEmoji": "📌",
    "subcats": [],
    "date": "2026-09-30",
    "endDate": "2026-09-30",
    "dateText": "30 sept. à 19:00",
    "schedule": "19h",
    "place": "10 rue du Baron Louis",
    "city": "Nancy",
    "free": false,
    "reservation": false,
    "image": "images/fb/837481552575582.jpg",
    "url": "https://www.facebook.com/events/837481552575582/",
    "source": "facebook",
    "rsvp": "",
    "online": false
  },
  {
    "uuid": "fb-26521390707470121",
    "title": "Olivier de Benoist • Salle Poirel, Nancy • 01/10/2026",
    "category": "musiques-actuelles",
    "catLabel": "Musiques actuelles",
    "catEmoji": "🎸",
    "subcats": [],
    "date": "2026-10-01",
    "endDate": "2026-10-01",
    "dateText": "1 oct. à 20:00",
    "schedule": "20h",
    "place": "Poirel",
    "city": "Nancy",
    "free": false,
    "reservation": false,
    "image": "images/fb/26521390707470121.jpg",
    "url": "https://www.facebook.com/events/26521390707470121/",
    "source": "facebook",
    "rsvp": "",
    "online": false
  },
  {
    "uuid": "fb-1424673519195684",
    "title": "The Sisters Of Mercy • L'Autre Canal Nancy",
    "category": "autre",
    "catLabel": "Autre",
    "catEmoji": "📌",
    "subcats": [],
    "date": "2026-10-02",
    "endDate": "2026-10-02",
    "dateText": "2 oct. à 20:00",
    "schedule": "20h",
    "place": "L'Autre Canal Nancy",
    "city": "Nancy",
    "free": false,
    "reservation": false,
    "image": "images/fb/1424673519195684.jpg",
    "url": "https://www.facebook.com/events/1424673519195684/",
    "source": "facebook",
    "rsvp": "",
    "online": false
  },
  {
    "uuid": "fb-851176187888286",
    "title": "DYSTOPIK FESTIVAL - 2ème édition",
    "category": "festival",
    "catLabel": "Festivals",
    "catEmoji": "🎪",
    "subcats": [],
    "date": "2026-10-02",
    "endDate": "2026-10-02",
    "dateText": "2 oct. - 3 oct.",
    "schedule": "",
    "place": "La BrÂss'",
    "city": "",
    "free": false,
    "reservation": false,
    "image": "images/fb/851176187888286.jpg",
    "url": "https://www.facebook.com/events/851176187888286/",
    "source": "facebook",
    "rsvp": "",
    "online": false
  },
  {
    "uuid": "fb-33830915003222650",
    "title": "Nancy ink tattoo",
    "category": "autre",
    "catLabel": "Autre",
    "catEmoji": "📌",
    "subcats": [],
    "date": "2026-10-03",
    "endDate": "2026-10-03",
    "dateText": "3 oct. à 10:00",
    "schedule": "10h",
    "place": "47 Bd d’Austrasie",
    "city": "Nancy",
    "free": false,
    "reservation": false,
    "image": "images/fb/33830915003222650.jpg",
    "url": "https://www.facebook.com/events/33830915003222650/",
    "source": "facebook",
    "rsvp": "",
    "online": false
  },
  {
    "uuid": "fb-2451986068648487",
    "title": "Stage de reliure \"CARNET CRISS-CROSS\"",
    "category": "activite",
    "catLabel": "Activités & ateliers",
    "catEmoji": "🎨",
    "subcats": [],
    "date": "2026-10-03",
    "endDate": "2026-10-03",
    "dateText": "3 oct. à 09:00",
    "schedule": "9h",
    "place": "35 rue de la Commanderie",
    "city": "Nancy",
    "free": false,
    "reservation": false,
    "image": "images/fb/2451986068648487.jpg",
    "url": "https://www.facebook.com/events/2451986068648487/",
    "source": "facebook",
    "rsvp": "",
    "online": false
  },
  {
    "uuid": "fb-1305080761550864",
    "title": "NANCY - Salon Bien-être, Nutrition, Santé, Médecines Douces au PARC DES EXPOS - OCTOBRE 2026",
    "category": "exposition",
    "catLabel": "Expositions",
    "catEmoji": "🖼️",
    "subcats": [],
    "date": "2026-10-03",
    "endDate": "2026-10-03",
    "dateText": "3 oct. - 4 oct.",
    "schedule": "",
    "place": "Parc des expositions Nancy",
    "city": "Nancy",
    "free": false,
    "reservation": false,
    "image": "images/fb/1305080761550864.jpg",
    "url": "https://www.facebook.com/events/1305080761550864/",
    "source": "facebook",
    "rsvp": "",
    "online": false
  },
  {
    "uuid": "fb-1328262165361819",
    "title": "BOUMSHAKALAKA · NANCY JAZZ KIDS",
    "category": "musiques-actuelles",
    "catLabel": "Musiques actuelles",
    "catEmoji": "🎸",
    "subcats": [],
    "date": "2026-10-03",
    "endDate": "2026-10-03",
    "dateText": "3 oct. à 10:00",
    "schedule": "10h",
    "place": "Parc de la Pépinière",
    "city": "Nancy",
    "free": false,
    "reservation": false,
    "image": "images/fb/1328262165361819.jpg",
    "url": "https://www.facebook.com/events/1328262165361819/",
    "source": "facebook",
    "rsvp": "",
    "online": false
  },
  {
    "uuid": "fb-694756763462089",
    "title": "Hypnose au Cinéma - Nancy - Cinéma Kinepolis",
    "category": "conference",
    "catLabel": "Conférences & rencontres",
    "catEmoji": "🎓",
    "subcats": [],
    "date": "2026-10-03",
    "endDate": "2026-10-03",
    "dateText": "3 oct. à 20:30",
    "schedule": "20h30",
    "place": "Kinepolis Nancy",
    "city": "Nancy",
    "free": false,
    "reservation": false,
    "image": "images/fb/694756763462089.jpg",
    "url": "https://www.facebook.com/events/694756763462089/",
    "source": "facebook",
    "rsvp": "",
    "online": false
  },
  {
    "uuid": "fb-1021631926868719",
    "title": "FILLE OU GARÇON ? · NANCY JAZZ KIDS",
    "category": "musiques-actuelles",
    "catLabel": "Musiques actuelles",
    "catEmoji": "🎸",
    "subcats": [],
    "date": "2026-10-04",
    "endDate": "2026-10-04",
    "dateText": "4 oct. à 15:00",
    "schedule": "15h",
    "place": "Parc de la Pépinière",
    "city": "Nancy",
    "free": false,
    "reservation": false,
    "image": "images/fb/1021631926868719.jpg",
    "url": "https://www.facebook.com/events/1021631926868719/",
    "source": "facebook",
    "rsvp": "",
    "online": false
  },
  {
    "uuid": "fb-808670078781391",
    "title": "BA-ba du bénévolat à l'Atelier des solidarités",
    "category": "activite",
    "catLabel": "Activités & ateliers",
    "catEmoji": "🎨",
    "subcats": [],
    "date": "2026-10-05",
    "endDate": "2026-10-05",
    "dateText": "5 oct. à 19:00",
    "schedule": "19h",
    "place": "32 rue Sainte-Anne",
    "city": "Nancy",
    "free": false,
    "reservation": false,
    "image": "images/fb/808670078781391.jpg",
    "url": "https://www.facebook.com/events/808670078781391/",
    "source": "facebook",
    "rsvp": "",
    "online": false
  },
  {
    "uuid": "fb-2255993398272223",
    "title": "CHRISTIAN MCBRIDE & URSA MAJOR + AMY GADIAGA · Poirel · NJP 2026",
    "category": "autre",
    "catLabel": "Autre",
    "catEmoji": "📌",
    "subcats": [],
    "date": "2026-10-07",
    "endDate": "2026-10-07",
    "dateText": "7 oct. à 20:00",
    "schedule": "20h",
    "place": "Poirel",
    "city": "",
    "free": false,
    "reservation": false,
    "image": "images/fb/2255993398272223.jpg",
    "url": "https://www.facebook.com/events/2255993398272223/",
    "source": "facebook",
    "rsvp": "",
    "online": false
  },
  {
    "uuid": "fb-4259820934330769",
    "title": "TROIS PETITS PAS · NANCY JAZZ KIDS",
    "category": "musiques-actuelles",
    "catLabel": "Musiques actuelles",
    "catEmoji": "🎸",
    "subcats": [],
    "date": "2026-10-07",
    "endDate": "2026-10-07",
    "dateText": "7 oct. à 10:00",
    "schedule": "10h",
    "place": "Parc de la Pépinière",
    "city": "Nancy",
    "free": false,
    "reservation": false,
    "image": "images/fb/4259820934330769.jpg",
    "url": "https://www.facebook.com/events/4259820934330769/",
    "source": "facebook",
    "rsvp": "",
    "online": false
  },
  {
    "uuid": "fb-2155195598546703",
    "title": "BD-CONCERT ÉMILE LONDONIEN X PIERRE-HENRY GOMONT · L’Autre Canal · CRÉATION NJP 2026",
    "category": "musiques-actuelles",
    "catLabel": "Musiques actuelles",
    "catEmoji": "🎸",
    "subcats": [],
    "date": "2026-10-08",
    "endDate": "2026-10-08",
    "dateText": "8 oct. à 20:30",
    "schedule": "20h30",
    "place": "L'Autre Canal Nancy",
    "city": "Nancy",
    "free": false,
    "reservation": false,
    "image": "images/fb/2155195598546703.jpg",
    "url": "https://www.facebook.com/events/2155195598546703/",
    "source": "facebook",
    "rsvp": "",
    "online": false
  },
  {
    "uuid": "fb-2051877735428948",
    "title": "BERTRAND BELIN + CHARLIE WINSTON (solo) + ALAIN CHAMFORT · Chapiteau · NJP 2026",
    "category": "musiques-actuelles",
    "catLabel": "Musiques actuelles",
    "catEmoji": "🎸",
    "subcats": [],
    "date": "2026-10-08",
    "endDate": "2026-10-08",
    "dateText": "8 oct. à 20:00",
    "schedule": "20h",
    "place": "Parc de la Pépinière",
    "city": "",
    "free": false,
    "reservation": false,
    "image": "images/fb/2051877735428948.jpg",
    "url": "https://www.facebook.com/events/2051877735428948/",
    "source": "facebook",
    "rsvp": "",
    "online": false
  },
  {
    "uuid": "fb-991234613800924",
    "title": "YAEL NAIM + MERYEM ABOULOUAFA · Poirel · NJP 2026",
    "category": "musiques-actuelles",
    "catLabel": "Musiques actuelles",
    "catEmoji": "🎸",
    "subcats": [],
    "date": "2026-10-08",
    "endDate": "2026-10-08",
    "dateText": "8 oct. à 20:00",
    "schedule": "20h",
    "place": "Poirel",
    "city": "",
    "free": false,
    "reservation": false,
    "image": "images/fb/991234613800924.jpg",
    "url": "https://www.facebook.com/events/991234613800924/",
    "source": "facebook",
    "rsvp": "",
    "online": false
  },
  {
    "uuid": "fb-1198117575566443",
    "title": "Formation « troubles neuro développementaux de l’enfant »",
    "category": "autre",
    "catLabel": "Autre",
    "catEmoji": "📌",
    "subcats": [],
    "date": "2026-10-08",
    "endDate": "2026-10-08",
    "dateText": "8 oct. - 10 oct.",
    "schedule": "",
    "place": "4",
    "city": "Nancy",
    "free": false,
    "reservation": false,
    "image": "images/fb/1198117575566443.jpg",
    "url": "https://www.facebook.com/events/1198117575566443/",
    "source": "facebook",
    "rsvp": "",
    "online": false
  },
  {
    "uuid": "fb-1945500236078228",
    "title": "MOSES YOOFEE TRIO + KAU · Magic · NJP 2026",
    "category": "autre",
    "catLabel": "Autre",
    "catEmoji": "📌",
    "subcats": [],
    "date": "2026-10-08",
    "endDate": "2026-10-08",
    "dateText": "8 oct. à 23:45",
    "schedule": "23h45",
    "place": "Parc de la Pépinière",
    "city": "",
    "free": false,
    "reservation": false,
    "image": "images/fb/1945500236078228.jpg",
    "url": "https://www.facebook.com/events/1945500236078228/",
    "source": "facebook",
    "rsvp": "",
    "online": false
  },
  {
    "uuid": "fb-1431927888479037",
    "title": "The Grand Express 2026 [WSDC Trial Event]",
    "category": "autre",
    "catLabel": "Autre",
    "catEmoji": "📌",
    "subcats": [],
    "date": "2026-10-08",
    "endDate": "2026-10-08",
    "dateText": "8 oct. à 21:00",
    "schedule": "21h",
    "place": "1 Place de la République",
    "city": "Nancy",
    "free": false,
    "reservation": false,
    "image": "images/fb/1431927888479037.jpg",
    "url": "https://www.facebook.com/events/1431927888479037/",
    "source": "facebook",
    "rsvp": "",
    "online": false
  },
  {
    "uuid": "fb-1481664679461355",
    "title": "DUB INC + THK + BLEU SOLEIL · Chapiteau · NJP 2026",
    "category": "autre",
    "catLabel": "Autre",
    "catEmoji": "📌",
    "subcats": [],
    "date": "2026-10-09",
    "endDate": "2026-10-09",
    "dateText": "9 oct. à 20:00",
    "schedule": "20h",
    "place": "Parc de la Pépinière",
    "city": "",
    "free": false,
    "reservation": false,
    "image": "images/fb/1481664679461355.jpg",
    "url": "https://www.facebook.com/events/1481664679461355/",
    "source": "facebook",
    "rsvp": "",
    "online": false
  },
  {
    "uuid": "fb-997389952698329",
    "title": "MÉDINE · ENFANTS DU DESTIN (TOURNÉE ACOUSTIQUE) + DORI · Poirel · NJP 2026",
    "category": "musiques-actuelles",
    "catLabel": "Musiques actuelles",
    "catEmoji": "🎸",
    "subcats": [],
    "date": "2026-10-09",
    "endDate": "2026-10-09",
    "dateText": "9 oct. à 20:00",
    "schedule": "20h",
    "place": "Poirel",
    "city": "",
    "free": false,
    "reservation": false,
    "image": "images/fb/997389952698329.jpg",
    "url": "https://www.facebook.com/events/997389952698329/",
    "source": "facebook",
    "rsvp": "",
    "online": false
  },
  {
    "uuid": "fb-1509958780638965",
    "title": "KULEEANGEE + NORD//NOIR + SARRA WILD · Magic · NJP 2026",
    "category": "autre",
    "catLabel": "Autre",
    "catEmoji": "📌",
    "subcats": [],
    "date": "2026-10-09",
    "endDate": "2026-10-09",
    "dateText": "9 oct. à 23:45",
    "schedule": "23h45",
    "place": "Parc de la Pépinière",
    "city": "",
    "free": false,
    "reservation": false,
    "image": "images/fb/1509958780638965.jpg",
    "url": "https://www.facebook.com/events/1509958780638965/",
    "source": "facebook",
    "rsvp": "",
    "online": false
  },
  {
    "uuid": "fb-1308957371393770",
    "title": "BON ENTENDEUR + GUESTS · L’Autre Canal · NJP 2026",
    "category": "autre",
    "catLabel": "Autre",
    "catEmoji": "📌",
    "subcats": [],
    "date": "2026-10-10",
    "endDate": "2026-10-10",
    "dateText": "10 oct. à 22:00",
    "schedule": "22h",
    "place": "L'Autre Canal Nancy",
    "city": "Nancy",
    "free": false,
    "reservation": false,
    "image": "images/fb/1308957371393770.jpg",
    "url": "https://www.facebook.com/events/1308957371393770/",
    "source": "facebook",
    "rsvp": "",
    "online": false
  },
  {
    "uuid": "fb-1628107684912190",
    "title": "HOUDI + LA RVFLEUZE + JUSTE SHANI · Chapiteau · NJP 2026",
    "category": "autre",
    "catLabel": "Autre",
    "catEmoji": "📌",
    "subcats": [],
    "date": "2026-10-10",
    "endDate": "2026-10-10",
    "dateText": "10 oct. à 20:00",
    "schedule": "20h",
    "place": "Parc de la Pépinière",
    "city": "",
    "free": false,
    "reservation": false,
    "image": "images/fb/1628107684912190.jpg",
    "url": "https://www.facebook.com/events/1628107684912190/",
    "source": "facebook",
    "rsvp": "",
    "online": false
  },
  {
    "uuid": "fb-4252045761752614",
    "title": "MONSTER FLORENCE + HYPNOSIS THERAPY + VIIAK · Magic · NJP 2026",
    "category": "musiques-actuelles",
    "catLabel": "Musiques actuelles",
    "catEmoji": "🎸",
    "subcats": [],
    "date": "2026-10-10",
    "endDate": "2026-10-10",
    "dateText": "10 oct. à 23:45",
    "schedule": "23h45",
    "place": "Parc de la Pépinière",
    "city": "",
    "free": false,
    "reservation": false,
    "image": "images/fb/4252045761752614.jpg",
    "url": "https://www.facebook.com/events/4252045761752614/",
    "source": "facebook",
    "rsvp": "",
    "online": false
  },
  {
    "uuid": "fb-1034580272231977",
    "title": "VINCENT PEIRANI + JUNGLE BY NIGHT · Poirel · NJP 2026",
    "category": "autre",
    "catLabel": "Autre",
    "catEmoji": "📌",
    "subcats": [],
    "date": "2026-10-10",
    "endDate": "2026-10-10",
    "dateText": "10 oct. à 20:00",
    "schedule": "20h",
    "place": "Poirel",
    "city": "",
    "free": false,
    "reservation": false,
    "image": "images/fb/1034580272231977.jpg",
    "url": "https://www.facebook.com/events/1034580272231977/",
    "source": "facebook",
    "rsvp": "",
    "online": false
  },
  {
    "uuid": "fb-1498395268730196",
    "title": "MAMMAL HANDS + SVANEBORG KARDYB · Manufacture · NJP 2026",
    "category": "spectacle",
    "catLabel": "Spectacles",
    "catEmoji": "🎭",
    "subcats": [],
    "date": "2026-10-12",
    "endDate": "2026-10-12",
    "dateText": "12 oct. à 20:00",
    "schedule": "20h",
    "place": "CDN Nancy Lorraine",
    "city": "Nancy",
    "free": false,
    "reservation": false,
    "image": "images/fb/1498395268730196.jpg",
    "url": "https://www.facebook.com/events/1498395268730196/",
    "source": "facebook",
    "rsvp": "",
    "online": false
  },
  {
    "uuid": "fb-1375668940988142",
    "title": "Temples • L'Autre Canal Nancy",
    "category": "autre",
    "catLabel": "Autre",
    "catEmoji": "📌",
    "subcats": [],
    "date": "2026-10-13",
    "endDate": "2026-10-13",
    "dateText": "13 oct. à 20:30",
    "schedule": "20h30",
    "place": "45",
    "city": "Nancy",
    "free": false,
    "reservation": false,
    "image": "images/fb/1375668940988142.jpg",
    "url": "https://www.facebook.com/events/1375668940988142/",
    "source": "facebook",
    "rsvp": "",
    "online": false
  },
  {
    "uuid": "fb-1297754748447867",
    "title": "SUZANE + MIKI + CAMILLE YEMBE · Chapiteau · NJP 2026",
    "category": "musiques-actuelles",
    "catLabel": "Musiques actuelles",
    "catEmoji": "🎸",
    "subcats": [],
    "date": "2026-10-13",
    "endDate": "2026-10-13",
    "dateText": "13 oct. à 20:00",
    "schedule": "20h",
    "place": "Parc de la Pépinière",
    "city": "",
    "free": false,
    "reservation": false,
    "image": "images/fb/1297754748447867.jpg",
    "url": "https://www.facebook.com/events/1297754748447867/",
    "source": "facebook",
    "rsvp": "",
    "online": false
  },
  {
    "uuid": "fb-4175517555911594",
    "title": "FERDI + FORWARD · Manufacture · NJP 2026",
    "category": "spectacle",
    "catLabel": "Spectacles",
    "catEmoji": "🎭",
    "subcats": [],
    "date": "2026-10-13",
    "endDate": "2026-10-13",
    "dateText": "13 oct. à 20:00",
    "schedule": "20h",
    "place": "CDN Nancy Lorraine",
    "city": "Nancy",
    "free": false,
    "reservation": false,
    "image": "images/fb/4175517555911594.jpg",
    "url": "https://www.facebook.com/events/4175517555911594/",
    "source": "facebook",
    "rsvp": "",
    "online": false
  },
  {
    "uuid": "fb-1521473196040038",
    "title": "ALELA DIANE + BIRDS ON A WIRE · Opéra · NJP 2026",
    "category": "musique-classique",
    "catLabel": "Musique classique",
    "catEmoji": "🎻",
    "subcats": [],
    "date": "2026-10-13",
    "endDate": "2026-10-13",
    "dateText": "13 oct. à 20:30",
    "schedule": "20h30",
    "place": "Opéra national de Nancy-Lorraine",
    "city": "Nancy",
    "free": false,
    "reservation": false,
    "image": "images/fb/1521473196040038.jpg",
    "url": "https://www.facebook.com/events/1521473196040038/",
    "source": "facebook",
    "rsvp": "",
    "online": false
  },
  {
    "uuid": "fb-1853789371931838",
    "title": "ASFAR SHAMSI + ENCORE UNE AUTRE · Magic · NJP 2026",
    "category": "musiques-actuelles",
    "catLabel": "Musiques actuelles",
    "catEmoji": "🎸",
    "subcats": [],
    "date": "2026-10-13",
    "endDate": "2026-10-13",
    "dateText": "13 oct. à 23:45",
    "schedule": "23h45",
    "place": "Parc de la Pépinière",
    "city": "",
    "free": false,
    "reservation": false,
    "image": "images/fb/1853789371931838.jpg",
    "url": "https://www.facebook.com/events/1853789371931838/",
    "source": "facebook",
    "rsvp": "",
    "online": false
  },
  {
    "uuid": "fb-1292449972415898",
    "title": "PETER DOHERTY (full band) + SAM SAUVAGE + JAMES BAKER · Chapiteau · NJP 2026",
    "category": "autre",
    "catLabel": "Autre",
    "catEmoji": "📌",
    "subcats": [],
    "date": "2026-10-14",
    "endDate": "2026-10-14",
    "dateText": "14 oct. à 20:00",
    "schedule": "20h",
    "place": "Parc de la Pépinière",
    "city": "",
    "free": false,
    "reservation": false,
    "image": "images/fb/1292449972415898.jpg",
    "url": "https://www.facebook.com/events/1292449972415898/",
    "source": "facebook",
    "rsvp": "",
    "online": false
  },
  {
    "uuid": "fb-26994296756926855",
    "title": "OPUS KINK + HEAVEN FX · Magic · NJP 2026",
    "category": "autre",
    "catLabel": "Autre",
    "catEmoji": "📌",
    "subcats": [],
    "date": "2026-10-14",
    "endDate": "2026-10-14",
    "dateText": "14 oct. à 23:45",
    "schedule": "23h45",
    "place": "Parc de la Pépinière",
    "city": "",
    "free": false,
    "reservation": false,
    "image": "images/fb/26994296756926855.jpg",
    "url": "https://www.facebook.com/events/26994296756926855/",
    "source": "facebook",
    "rsvp": "",
    "online": false
  },
  {
    "uuid": "fb-1869275677100065",
    "title": "DHAFER YOUSSEF · Opéra · NJP 2026",
    "category": "musique-classique",
    "catLabel": "Musique classique",
    "catEmoji": "🎻",
    "subcats": [],
    "date": "2026-10-14",
    "endDate": "2026-10-14",
    "dateText": "14 oct. à 20:30",
    "schedule": "20h30",
    "place": "Opéra national de Nancy-Lorraine",
    "city": "Nancy",
    "free": false,
    "reservation": false,
    "image": "images/fb/1869275677100065.jpg",
    "url": "https://www.facebook.com/events/1869275677100065/",
    "source": "facebook",
    "rsvp": "",
    "online": false
  },
  {
    "uuid": "fb-1579125533633874",
    "title": "CÉLIA KAMENI + MELISSA WEIKART (SOLO) · Manufacture · NJP 2026",
    "category": "musiques-actuelles",
    "catLabel": "Musiques actuelles",
    "catEmoji": "🎸",
    "subcats": [],
    "date": "2026-10-14",
    "endDate": "2026-10-14",
    "dateText": "14 oct. à 20:00",
    "schedule": "20h",
    "place": "CDN Nancy Lorraine",
    "city": "Nancy",
    "free": false,
    "reservation": false,
    "image": "images/fb/1579125533633874.jpg",
    "url": "https://www.facebook.com/events/1579125533633874/",
    "source": "facebook",
    "rsvp": "",
    "online": false
  },
  {
    "uuid": "fb-1724783158947031",
    "title": "ALTIN GÜN + YUUF · L’Autre Canal · NJP 2026",
    "category": "autre",
    "catLabel": "Autre",
    "catEmoji": "📌",
    "subcats": [],
    "date": "2026-10-15",
    "endDate": "2026-10-15",
    "dateText": "15 oct. à 20:00",
    "schedule": "20h",
    "place": "L'Autre Canal Nancy",
    "city": "Nancy",
    "free": false,
    "reservation": false,
    "image": "images/fb/1724783158947031.jpg",
    "url": "https://www.facebook.com/events/1724783158947031/",
    "source": "facebook",
    "rsvp": "",
    "online": false
  },
  {
    "uuid": "fb-1342811444380931",
    "title": "PINK MARTINI + HAROLD LÓPEZ-NUSSA + FLORE BENGUIGUI & THE SENSIBLE NOTES · Chapiteau · NJP 2026",
    "category": "autre",
    "catLabel": "Autre",
    "catEmoji": "📌",
    "subcats": [],
    "date": "2026-10-15",
    "endDate": "2026-10-15",
    "dateText": "15 oct. à 20:00",
    "schedule": "20h",
    "place": "Parc de la Pépinière",
    "city": "",
    "free": false,
    "reservation": false,
    "image": "images/fb/1342811444380931.jpg",
    "url": "https://www.facebook.com/events/1342811444380931/",
    "source": "facebook",
    "rsvp": "",
    "online": false
  },
  {
    "uuid": "fb-1633736961220025",
    "title": "DAME AREA + JUNGLIST NANCY · Magic · NJP 2026",
    "category": "autre",
    "catLabel": "Autre",
    "catEmoji": "📌",
    "subcats": [],
    "date": "2026-10-15",
    "endDate": "2026-10-15",
    "dateText": "15 oct. à 23:45",
    "schedule": "23h45",
    "place": "Parc de la Pépinière",
    "city": "Nancy",
    "free": false,
    "reservation": false,
    "image": "images/fb/1633736961220025.jpg",
    "url": "https://www.facebook.com/events/1633736961220025/",
    "source": "facebook",
    "rsvp": "",
    "online": false
  },
  {
    "uuid": "fb-956284790564879",
    "title": "NDUDUZO MAKHATHINI + STRANDED HORSE & BOUBACAR CISSOKHO · Manufacture · NJP 2026",
    "category": "musiques-actuelles",
    "catLabel": "Musiques actuelles",
    "catEmoji": "🎸",
    "subcats": [],
    "date": "2026-10-15",
    "endDate": "2026-10-15",
    "dateText": "15 oct. à 20:00",
    "schedule": "20h",
    "place": "CDN Nancy Lorraine",
    "city": "Nancy",
    "free": false,
    "reservation": false,
    "image": "images/fb/956284790564879.jpg",
    "url": "https://www.facebook.com/events/956284790564879/",
    "source": "facebook",
    "rsvp": "",
    "online": false
  },
  {
    "uuid": "fb-998758786095997",
    "title": "J'AI RIEN DEMANDÉ MOI",
    "category": "autre",
    "catLabel": "Autre",
    "catEmoji": "📌",
    "subcats": [],
    "date": "2026-10-15",
    "endDate": "2026-10-15",
    "dateText": "15 oct. à 14:30",
    "schedule": "14h30",
    "place": "10 rue du Baron Louis",
    "city": "Nancy",
    "free": false,
    "reservation": false,
    "image": "images/fb/998758786095997.jpg",
    "url": "https://www.facebook.com/events/998758786095997/",
    "source": "facebook",
    "rsvp": "",
    "online": false
  }
]
